<annotation><folder>frames</folder><filename>test_frame13</filename><path>/frames/test_frame13</path><source><database>Unknown</database></source><size><width>1920</width><height>1080</height><depth>3</depth></size><segmented>0</segmented><object><name>bee</name><pose>Unspecified</pose><truncated>0</truncated><difficult>0</difficult><bndbox><xmin>51</xmin><ymin>867</ymin><xmax>203</xmax><ymax>1019</ymax></bndbox></object><object><name>bee</name><pose>Unspecified</pose><truncated>0</truncated><difficult>0</difficult><bndbox><xmin>0</xmin><ymin>867</ymin><xmax>152</xmax><ymax>1019</ymax></bndbox></object><object><name>bee</name><pose>Unspecified</pose><truncated>0</truncated><difficult>0</difficult><bndbox><xmin>102</xmin><ymin>867</ymin><xmax>254</xmax><ymax>1019</ymax></bndbox></object><object><name>bee</name><pose>Unspecified</pose><truncated>0</truncated><difficult>0</difficult><bndbox><xmin>178</xmin><ymin>867</ymin><xmax>330</xmax><ymax>1019</ymax></bndbox></object><object><name>bee</name><pose>Unspecified</pose><truncated>0</truncated><difficult>0</difficult><bndbox><xmin>344</xmin><ymin>881</ymin><xmax>472</xmax><ymax>1009</ymax></bndbox></object><object><name>bee</name><pose>Unspecified</pose><truncated>0</truncated><difficult>0</difficult><bndbox><xmin>255</xmin><ymin>867</ymin><xmax>407</xmax><ymax>1019</ymax></bndbox></object><object><name>bee</name><pose>Unspecified</pose><truncated>0</truncated><difficult>0</difficult><bndbox><xmin>387</xmin><ymin>881</ymin><xmax>515</xmax><ymax>1009</ymax></bndbox></object><object><name>bee</name><pose>Unspecified</pose><truncated>0</truncated><difficult>0</difficult><bndbox><xmin>510</xmin><ymin>867</ymin><xmax>662</xmax><ymax>1019</ymax></bndbox></object><object><name>bee</name><pose>Unspecified</pose><truncated>0</truncated><difficult>0</difficult><bndbox><xmin>473</xmin><ymin>881</ymin><xmax>601</xmax><ymax>1009</ymax></bndbox></object><object><name>bee</name><pose>Unspecified</pose><truncated>0</truncated><difficult>0</difficult><bndbox><xmin>576</xmin><ymin>894</ymin><xmax>666</xmax><ymax>984</ymax></bndbox></object><object><name>bee</name><pose>Unspecified</pose><truncated>0</truncated><difficult>0</difficult><bndbox><xmin>640</xmin><ymin>823</ymin><xmax>822</xmax><ymax>1005</ymax></bndbox></object><object><name>bee</name><pose>Unspecified</pose><truncated>0</truncated><difficult>0</difficult><bndbox><xmin>616</xmin><ymin>898</ymin><xmax>692</xmax><ymax>974</ymax></bndbox></object><object><name>bee</name><pose>Unspecified</pose><truncated>0</truncated><difficult>0</difficult><bndbox><xmin>712</xmin><ymin>91</ymin><xmax>802</xmax><ymax>181</ymax></bndbox></object><object><name>bee</name><pose>Unspecified</pose><truncated>0</truncated><difficult>0</difficult><bndbox><xmin>817</xmin><ymin>872</ymin><xmax>925</xmax><ymax>980</ymax></bndbox></object><object><name>bee</name><pose>Unspecified</pose><truncated>0</truncated><difficult>0</difficult><bndbox><xmin>763</xmin><ymin>890</ymin><xmax>871</xmax><ymax>998</ymax></bndbox></object><object><name>bee</name><pose>Unspecified</pose><truncated>0</truncated><difficult>0</difficult><bndbox><xmin>925</xmin><ymin>879</ymin><xmax>1015</xmax><ymax>969</ymax></bndbox></object><object><name>bee</name><pose>Unspecified</pose><truncated>0</truncated><difficult>0</difficult><bndbox><xmin>985</xmin><ymin>879</ymin><xmax>1075</xmax><ymax>969</ymax></bndbox></object><object><name>bee</name><pose>Unspecified</pose><truncated>0</truncated><difficult>0</difficult><bndbox><xmin>955</xmin><ymin>894</ymin><xmax>1045</xmax><ymax>984</ymax></bndbox></object><object><name>bee</name><pose>Unspecified</pose><truncated>0</truncated><difficult>0</difficult><bndbox><xmin>1053</xmin><ymin>860</ymin><xmax>1181</xmax><ymax>988</ymax></bndbox></object><object><name>bee</name><pose>Unspecified</pose><truncated>0</truncated><difficult>0</difficult><bndbox><xmin>1139</xmin><ymin>860</ymin><xmax>1267</xmax><ymax>988</ymax></bndbox></object><object><name>bee</name><pose>Unspecified</pose><truncated>0</truncated><difficult>0</difficult><bndbox><xmin>1173</xmin><ymin>867</ymin><xmax>1325</xmax><ymax>1019</ymax></bndbox></object><object><name>bee</name><pose>Unspecified</pose><truncated>0</truncated><difficult>0</difficult><bndbox><xmin>1311</xmin><ymin>823</ymin><xmax>1493</xmax><ymax>1005</ymax></bndbox></object><object><name>bee</name><pose>Unspecified</pose><truncated>0</truncated><difficult>0</difficult><bndbox><xmin>1243</xmin><ymin>894</ymin><xmax>1333</xmax><ymax>984</ymax></bndbox></object><object><name>bee</name><pose>Unspecified</pose><truncated>0</truncated><difficult>0</difficult><bndbox><xmin>1268</xmin><ymin>860</ymin><xmax>1396</xmax><ymax>988</ymax></bndbox></object><object><name>bee</name><pose>Unspecified</pose><truncated>0</truncated><difficult>0</difficult><bndbox><xmin>1334</xmin><ymin>872</ymin><xmax>1410</xmax><ymax>948</ymax></bndbox></object><object><name>bee</name><pose>Unspecified</pose><truncated>0</truncated><difficult>0</difficult><bndbox><xmin>1377</xmin><ymin>841</ymin><xmax>1529</xmax><ymax>993</ymax></bndbox></object><object><name>bee</name><pose>Unspecified</pose><truncated>0</truncated><difficult>0</difficult><bndbox><xmin>1526</xmin><ymin>872</ymin><xmax>1634</xmax><ymax>980</ymax></bndbox></object><object><name>bee</name><pose>Unspecified</pose><truncated>0</truncated><difficult>0</difficult><bndbox><xmin>1591</xmin><ymin>860</ymin><xmax>1719</xmax><ymax>988</ymax></bndbox></object><object><name>bee</name><pose>Unspecified</pose><truncated>0</truncated><difficult>0</difficult><bndbox><xmin>1435</xmin><ymin>872</ymin><xmax>1543</xmax><ymax>980</ymax></bndbox></object><object><name>bee</name><pose>Unspecified</pose><truncated>0</truncated><difficult>0</difficult><bndbox><xmin>1514</xmin><ymin>872</ymin><xmax>1590</xmax><ymax>948</ymax></bndbox></object><object><name>bee</name><pose>Unspecified</pose><truncated>0</truncated><difficult>0</difficult><bndbox><xmin>1653</xmin><ymin>872</ymin><xmax>1761</xmax><ymax>980</ymax></bndbox></object><object><name>bee</name><pose>Unspecified</pose><truncated>0</truncated><difficult>0</difficult><bndbox><xmin>1719</xmin><ymin>872</ymin><xmax>1795</xmax><ymax>948</ymax></bndbox></object><object><name>bee</name><pose>Unspecified</pose><truncated>0</truncated><difficult>0</difficult><bndbox><xmin>1771</xmin><ymin>872</ymin><xmax>1847</xmax><ymax>948</ymax></bndbox></object><object><name>bee</name><pose>Unspecified</pose><truncated>0</truncated><difficult>0</difficult><bndbox><xmin>1835</xmin><ymin>872</ymin><xmax>1911</xmax><ymax>948</ymax></bndbox></object></annotation>