<annotation><folder>frames</folder><filename>test_frame49</filename><path>/frames/test_frame49</path><source><database>Unknown</database></source><size><width>1920</width><height>1080</height><depth>3</depth></size><segmented>0</segmented><object><name>bee</name><pose>Unspecified</pose><truncated>0</truncated><difficult>0</difficult><bndbox><xmin>25</xmin><ymin>867</ymin><xmax>177</xmax><ymax>1019</ymax></bndbox></object><object><name>bee</name><pose>Unspecified</pose><truncated>0</truncated><difficult>0</difficult><bndbox><xmin>76</xmin><ymin>867</ymin><xmax>228</xmax><ymax>1019</ymax></bndbox></object><object><name>bee</name><pose>Unspecified</pose><truncated>0</truncated><difficult>0</difficult><bndbox><xmin>43</xmin><ymin>899</ymin><xmax>107</xmax><ymax>963</ymax></bndbox></object><object><name>bee</name><pose>Unspecified</pose><truncated>0</truncated><difficult>0</difficult><bndbox><xmin>127</xmin><ymin>867</ymin><xmax>279</xmax><ymax>1019</ymax></bndbox></object><object><name>bee</name><pose>Unspecified</pose><truncated>0</truncated><difficult>0</difficult><bndbox><xmin>178</xmin><ymin>867</ymin><xmax>330</xmax><ymax>1019</ymax></bndbox></object><object><name>bee</name><pose>Unspecified</pose><truncated>0</truncated><difficult>0</difficult><bndbox><xmin>305</xmin><ymin>854</ymin><xmax>487</xmax><ymax>1036</ymax></bndbox></object><object><name>bee</name><pose>Unspecified</pose><truncated>0</truncated><difficult>0</difficult><bndbox><xmin>258</xmin><ymin>881</ymin><xmax>386</xmax><ymax>1009</ymax></bndbox></object><object><name>bee</name><pose>Unspecified</pose><truncated>0</truncated><difficult>0</difficult><bndbox><xmin>387</xmin><ymin>881</ymin><xmax>515</xmax><ymax>1009</ymax></bndbox></object><object><name>bee</name><pose>Unspecified</pose><truncated>0</truncated><difficult>0</difficult><bndbox><xmin>516</xmin><ymin>881</ymin><xmax>644</xmax><ymax>1009</ymax></bndbox></object><object><name>bee</name><pose>Unspecified</pose><truncated>0</truncated><difficult>0</difficult><bndbox><xmin>473</xmin><ymin>881</ymin><xmax>601</xmax><ymax>1009</ymax></bndbox></object><object><name>bee</name><pose>Unspecified</pose><truncated>0</truncated><difficult>0</difficult><bndbox><xmin>610</xmin><ymin>823</ymin><xmax>792</xmax><ymax>1005</ymax></bndbox></object><object><name>bee</name><pose>Unspecified</pose><truncated>0</truncated><difficult>0</difficult><bndbox><xmin>682</xmin><ymin>257</ymin><xmax>772</xmax><ymax>347</ymax></bndbox></object><object><name>bee</name><pose>Unspecified</pose><truncated>0</truncated><difficult>0</difficult><bndbox><xmin>704</xmin><ymin>866</ymin><xmax>768</xmax><ymax>930</ymax></bndbox></object><object><name>bee</name><pose>Unspecified</pose><truncated>0</truncated><difficult>0</difficult><bndbox><xmin>835</xmin><ymin>872</ymin><xmax>943</xmax><ymax>980</ymax></bndbox></object><object><name>bee</name><pose>Unspecified</pose><truncated>0</truncated><difficult>0</difficult><bndbox><xmin>731</xmin><ymin>881</ymin><xmax>859</xmax><ymax>1009</ymax></bndbox></object><object><name>bee</name><pose>Unspecified</pose><truncated>0</truncated><difficult>0</difficult><bndbox><xmin>739</xmin><ymin>510</ymin><xmax>891</xmax><ymax>662</ymax></bndbox></object><object><name>bee</name><pose>Unspecified</pose><truncated>0</truncated><difficult>0</difficult><bndbox><xmin>803</xmin><ymin>894</ymin><xmax>893</xmax><ymax>984</ymax></bndbox></object><object><name>bee</name><pose>Unspecified</pose><truncated>0</truncated><difficult>0</difficult><bndbox><xmin>925</xmin><ymin>894</ymin><xmax>1015</xmax><ymax>984</ymax></bndbox></object><object><name>bee</name><pose>Unspecified</pose><truncated>0</truncated><difficult>0</difficult><bndbox><xmin>1032</xmin><ymin>860</ymin><xmax>1160</xmax><ymax>988</ymax></bndbox></object><object><name>bee</name><pose>Unspecified</pose><truncated>0</truncated><difficult>0</difficult><bndbox><xmin>970</xmin><ymin>894</ymin><xmax>1060</xmax><ymax>984</ymax></bndbox></object><object><name>bee</name><pose>Unspecified</pose><truncated>0</truncated><difficult>0</difficult><bndbox><xmin>1107</xmin><ymin>879</ymin><xmax>1197</xmax><ymax>969</ymax></bndbox></object><object><name>bee</name><pose>Unspecified</pose><truncated>0</truncated><difficult>0</difficult><bndbox><xmin>1147</xmin><ymin>867</ymin><xmax>1299</xmax><ymax>1019</ymax></bndbox></object><object><name>bee</name><pose>Unspecified</pose><truncated>0</truncated><difficult>0</difficult><bndbox><xmin>1220</xmin><ymin>762</ymin><xmax>1402</xmax><ymax>944</ymax></bndbox></object><object><name>bee</name><pose>Unspecified</pose><truncated>0</truncated><difficult>0</difficult><bndbox><xmin>1257</xmin><ymin>885</ymin><xmax>1333</xmax><ymax>961</ymax></bndbox></object><object><name>bee</name><pose>Unspecified</pose><truncated>0</truncated><difficult>0</difficult><bndbox><xmin>1354</xmin><ymin>860</ymin><xmax>1482</xmax><ymax>988</ymax></bndbox></object><object><name>bee</name><pose>Unspecified</pose><truncated>0</truncated><difficult>0</difficult><bndbox><xmin>1296</xmin><ymin>795</ymin><xmax>1372</xmax><ymax>871</ymax></bndbox></object><object><name>bee</name><pose>Unspecified</pose><truncated>0</truncated><difficult>0</difficult><bndbox><xmin>1326</xmin><ymin>872</ymin><xmax>1434</xmax><ymax>980</ymax></bndbox></object><object><name>bee</name><pose>Unspecified</pose><truncated>0</truncated><difficult>0</difficult><bndbox><xmin>1397</xmin><ymin>860</ymin><xmax>1525</xmax><ymax>988</ymax></bndbox></object><object><name>bee</name><pose>Unspecified</pose><truncated>0</truncated><difficult>0</difficult><bndbox><xmin>1562</xmin><ymin>879</ymin><xmax>1652</xmax><ymax>969</ymax></bndbox></object><object><name>bee</name><pose>Unspecified</pose><truncated>0</truncated><difficult>0</difficult><bndbox><xmin>1471</xmin><ymin>872</ymin><xmax>1579</xmax><ymax>980</ymax></bndbox></object><object><name>bee</name><pose>Unspecified</pose><truncated>0</truncated><difficult>0</difficult><bndbox><xmin>1598</xmin><ymin>872</ymin><xmax>1706</xmax><ymax>980</ymax></bndbox></object><object><name>bee</name><pose>Unspecified</pose><truncated>0</truncated><difficult>0</difficult><bndbox><xmin>1653</xmin><ymin>872</ymin><xmax>1761</xmax><ymax>980</ymax></bndbox></object><object><name>bee</name><pose>Unspecified</pose><truncated>0</truncated><difficult>0</difficult><bndbox><xmin>1729</xmin><ymin>879</ymin><xmax>1819</xmax><ymax>969</ymax></bndbox></object><object><name>bee</name><pose>Unspecified</pose><truncated>0</truncated><difficult>0</difficult><bndbox><xmin>1784</xmin><ymin>860</ymin><xmax>1912</xmax><ymax>988</ymax></bndbox></object></annotation>