<annotation><folder>frames</folder><filename>frame678</filename><path>/frames/frame678</path><source><database>Unknown</database></source><size><width>1920</width><height>1080</height><depth>3</depth></size><segmented>0</segmented><object><name>bee</name><pose>Unspecified</pose><truncated>0</truncated><difficult>0</difficult><bndbox><xmin>563</xmin><ymin>619</ymin><xmax>663</xmax><ymax>719</ymax></bndbox></object><object><name>bee</name><pose>Unspecified</pose><truncated>0</truncated><difficult>0</difficult><bndbox><xmin>1136</xmin><ymin>566</ymin><xmax>1226</xmax><ymax>656</ymax></bndbox></object><object><name>bee</name><pose>Unspecified</pose><truncated>0</truncated><difficult>0</difficult><bndbox><xmin>61</xmin><ymin>205</ymin><xmax>127</xmax><ymax>271</ymax></bndbox></object></annotation>