<annotation verified="yes">
	<folder>frames</folder>
	<filename>frame1173.jpg</filename>
	<path>D:\mgr projekt\mgr\project\processing\frames\frame1173.jpg</path>
	<source>
		<database>Unknown</database>
	</source>
	<size>
		<width>1920</width>
		<height>1080</height>
		<depth>3</depth>
	</size>
	<segmented>0</segmented>
	<object>
		<name>bee</name>
		<pose>Unspecified</pose>
		<truncated>0</truncated>
		<difficult>0</difficult>
		<bndbox>
			<xmin>1040</xmin>
			<ymin>821</ymin>
			<xmax>1230</xmax>
			<ymax>953</ymax>
		</bndbox>
	</object>
	<object>
		<name>bee</name>
		<pose>Unspecified</pose>
		<truncated>0</truncated>
		<difficult>0</difficult>
		<bndbox>
			<xmin>1299</xmin>
			<ymin>831</ymin>
			<xmax>1485</xmax>
			<ymax>941</ymax>
		</bndbox>
	</object>
	<object>
		<name>bee</name>
		<pose>Unspecified</pose>
		<truncated>0</truncated>
		<difficult>0</difficult>
		<bndbox>
			<xmin>659</xmin>
			<ymin>815</ymin>
			<xmax>796</xmax>
			<ymax>948</ymax>
		</bndbox>
	</object>
	<object>
		<name>bee</name>
		<pose>Unspecified</pose>
		<truncated>0</truncated>
		<difficult>0</difficult>
		<bndbox>
			<xmin>700</xmin>
			<ymin>44</ymin>
			<xmax>883</xmax>
			<ymax>245</ymax>
		</bndbox>
	</object>
</annotation>
