<annotation><folder>frames</folder><filename>DSCN9952_frame381</filename><path>/frames/DSCN9952_frame381</path><source><database>Unknown</database></source><size><width>1920</width><height>1080</height><depth>3</depth></size><segmented>0</segmented><object><name>bee</name><pose>Unspecified</pose><truncated>0</truncated><difficult>0</difficult><bndbox><xmin>606</xmin><ymin>733</ymin><xmax>730</xmax><ymax>857</ymax></bndbox></object><object><name>bee</name><pose>Unspecified</pose><truncated>0</truncated><difficult>0</difficult><bndbox><xmin>1591</xmin><ymin>767</ymin><xmax>1723</xmax><ymax>899</ymax></bndbox></object><object><name>bee</name><pose>Unspecified</pose><truncated>0</truncated><difficult>0</difficult><bndbox><xmin>827</xmin><ymin>678</ymin><xmax>945</xmax><ymax>796</ymax></bndbox></object><object><name>bee</name><pose>Unspecified</pose><truncated>0</truncated><difficult>0</difficult><bndbox><xmin>137</xmin><ymin>44</ymin><xmax>249</xmax><ymax>156</ymax></bndbox></object></annotation>