<annotation><folder>frames</folder><filename>DSCN9956_frame3</filename><path>/frames/DSCN9956_frame3</path><source><database>Unknown</database></source><size><width>1920</width><height>1080</height><depth>3</depth></size><segmented>0</segmented><object><name>bee</name><pose>Unspecified</pose><truncated>0</truncated><difficult>0</difficult><bndbox><xmin>1282</xmin><ymin>202</ymin><xmax>1434</xmax><ymax>354</ymax></bndbox></object><object><name>bee</name><pose>Unspecified</pose><truncated>0</truncated><difficult>0</difficult><bndbox><xmin>1452</xmin><ymin>43</ymin><xmax>1602</xmax><ymax>193</ymax></bndbox></object></annotation>