<annotation><folder>frames</folder><filename>frame1502</filename><path>/frames/frame1502</path><source><database>Unknown</database></source><size><width>1920</width><height>1080</height><depth>3</depth></size><segmented>0</segmented><object><name>bee</name><pose>Unspecified</pose><truncated>0</truncated><difficult>0</difficult><bndbox><xmin>351</xmin><ymin>765</ymin><xmax>493</xmax><ymax>907</ymax></bndbox></object><object><name>bee</name><pose>Unspecified</pose><truncated>0</truncated><difficult>0</difficult><bndbox><xmin>1374</xmin><ymin>759</ymin><xmax>1518</xmax><ymax>903</ymax></bndbox></object><object><name>bee</name><pose>Unspecified</pose><truncated>0</truncated><difficult>0</difficult><bndbox><xmin>1547</xmin><ymin>764</ymin><xmax>1697</xmax><ymax>914</ymax></bndbox></object><object><name>bee</name><pose>Unspecified</pose><truncated>0</truncated><difficult>0</difficult><bndbox><xmin>57</xmin><ymin>771</ymin><xmax>195</xmax><ymax>909</ymax></bndbox></object></annotation>