<annotation><folder>frames</folder><filename>DSCN9954_frame838</filename><path>/frames/DSCN9954_frame838</path><source><database>Unknown</database></source><size><width>1920</width><height>1080</height><depth>3</depth></size><segmented>0</segmented><object><name>bee</name><pose>Unspecified</pose><truncated>0</truncated><difficult>0</difficult><bndbox><xmin>918</xmin><ymin>739</ymin><xmax>1090</xmax><ymax>911</ymax></bndbox></object><object><name>bee</name><pose>Unspecified</pose><truncated>0</truncated><difficult>0</difficult><bndbox><xmin>780</xmin><ymin>732</ymin><xmax>938</xmax><ymax>890</ymax></bndbox></object></annotation>