<annotation><folder>frames</folder><filename>frame3</filename><path>/frames/frame3</path><source><database>Unknown</database></source><size><width>1920</width><height>1080</height><depth>3</depth></size><segmented>0</segmented><object><name>bee</name><pose>Unspecified</pose><truncated>0</truncated><difficult>0</difficult><bndbox><xmin>543</xmin><ymin>333</ymin><xmax>719</xmax><ymax>509</ymax></bndbox></object><object><name>bee</name><pose>Unspecified</pose><truncated>0</truncated><difficult>0</difficult><bndbox><xmin>501</xmin><ymin>177</ymin><xmax>671</xmax><ymax>347</ymax></bndbox></object><object><name>bee</name><pose>Unspecified</pose><truncated>0</truncated><difficult>0</difficult><bndbox><xmin>678</xmin><ymin>514</ymin><xmax>858</xmax><ymax>694</ymax></bndbox></object></annotation>