<annotation><folder>frames</folder><filename>frame401</filename><path>/frames/frame401</path><source><database>Unknown</database></source><size><width>1920</width><height>1080</height><depth>3</depth></size><segmented>0</segmented><object><name>bee</name><pose>Unspecified</pose><truncated>0</truncated><difficult>0</difficult><bndbox><xmin>668</xmin><ymin>235</ymin><xmax>834</xmax><ymax>401</ymax></bndbox></object><object><name>bee</name><pose>Unspecified</pose><truncated>0</truncated><difficult>0</difficult><bndbox><xmin>1005</xmin><ymin>743</ymin><xmax>1159</xmax><ymax>897</ymax></bndbox></object><object><name>bee</name><pose>Unspecified</pose><truncated>0</truncated><difficult>0</difficult><bndbox><xmin>617</xmin><ymin>790</ymin><xmax>785</xmax><ymax>958</ymax></bndbox></object><object><name>bee</name><pose>Unspecified</pose><truncated>0</truncated><difficult>0</difficult><bndbox><xmin>820</xmin><ymin>769</ymin><xmax>978</xmax><ymax>927</ymax></bndbox></object><object><name>bee</name><pose>Unspecified</pose><truncated>0</truncated><difficult>0</difficult><bndbox><xmin>721</xmin><ymin>799</ymin><xmax>883</xmax><ymax>961</ymax></bndbox></object></annotation>