<annotation><folder>frames</folder><filename>DSCN9954_frame123</filename><path>/frames/DSCN9954_frame123</path><source><database>Unknown</database></source><size><width>1920</width><height>1080</height><depth>3</depth></size><segmented>0</segmented><object><name>bee</name><pose>Unspecified</pose><truncated>0</truncated><difficult>0</difficult><bndbox><xmin>903</xmin><ymin>501</ymin><xmax>1073</xmax><ymax>671</ymax></bndbox></object><object><name>bee</name><pose>Unspecified</pose><truncated>0</truncated><difficult>0</difficult><bndbox><xmin>615</xmin><ymin>457</ymin><xmax>785</xmax><ymax>627</ymax></bndbox></object></annotation>