<annotation><folder>frames</folder><filename>frame739.jpg</filename><path>D:/mgr projekt/mgr/project/processing/frames/frame739.jpg</path><source><database>Unknown</database></source><size><width>1920</width><height>1080</height><depth>3</depth></size><segmented>0</segmented><object><name>bee</name><pose>Unspecified</pose><truncated>0</truncated><difficult>0</difficult><bndbox><xmin>1243</xmin><ymin>1057</ymin><xmax>1283</xmax><ymax>1080</ymax></bndbox></object><object><name>bee</name><pose>Unspecified</pose><truncated>0</truncated><difficult>0</difficult><bndbox><xmin>820</xmin><ymin>1052</ymin><xmax>882</xmax><ymax>1080</ymax></bndbox></object><object><name>bee</name><pose>Unspecified</pose><truncated>0</truncated><difficult>0</difficult><bndbox><xmin>1284</xmin><ymin>1047</ymin><xmax>1319</xmax><ymax>1080</ymax></bndbox></object><object><name>bee</name><pose>Unspecified</pose><truncated>0</truncated><difficult>0</difficult><bndbox><xmin>1335</xmin><ymin>1044</ymin><xmax>1360</xmax><ymax>1068</ymax></bndbox></object><object><name>bee</name><pose>Unspecified</pose><truncated>0</truncated><difficult>0</difficult><bndbox><xmin>1755</xmin><ymin>1037</ymin><xmax>1806</xmax><ymax>1062</ymax></bndbox></object><object><name>bee</name><pose>Unspecified</pose><truncated>0</truncated><difficult>0</difficult><bndbox><xmin>1879</xmin><ymin>1032</ymin><xmax>1902</xmax><ymax>1056</ymax></bndbox></object><object><name>bee</name><pose>Unspecified</pose><truncated>0</truncated><difficult>0</difficult><bndbox><xmin>1021</xmin><ymin>983</ymin><xmax>1044</xmax><ymax>1005</ymax></bndbox></object><object><name>bee</name><pose>Unspecified</pose><truncated>0</truncated><difficult>0</difficult><bndbox><xmin>898</xmin><ymin>849</ymin><xmax>1040</xmax><ymax>1010</ymax></bndbox></object></annotation>