<annotation verified="yes">
	<folder>frames</folder>
	<filename>frame1070.jpg</filename>
	<path>D:\mgr projekt\mgr\project\processing\frames\frame1070.jpg</path>
	<source>
		<database>Unknown</database>
	</source>
	<size>
		<width>1920</width>
		<height>1080</height>
		<depth>3</depth>
	</size>
	<segmented>0</segmented>
	<object>
		<name>bee</name>
		<pose>Unspecified</pose>
		<truncated>0</truncated>
		<difficult>0</difficult>
		<bndbox>
			<xmin>1550</xmin>
			<ymin>726</ymin>
			<xmax>1710</xmax>
			<ymax>917</ymax>
		</bndbox>
	</object>
	<object>
		<name>bee</name>
		<pose>Unspecified</pose>
		<truncated>0</truncated>
		<difficult>0</difficult>
		<bndbox>
			<xmin>513</xmin>
			<ymin>475</ymin>
			<xmax>673</xmax>
			<ymax>677</ymax>
		</bndbox>
	</object>
	<object>
		<name>bee</name>
		<pose>Unspecified</pose>
		<truncated>0</truncated>
		<difficult>0</difficult>
		<bndbox>
			<xmin>924</xmin>
			<ymin>433</ymin>
			<xmax>1115</xmax>
			<ymax>633</ymax>
		</bndbox>
	</object>
	<object>
		<name>bee</name>
		<pose>Unspecified</pose>
		<truncated>0</truncated>
		<difficult>0</difficult>
		<bndbox>
			<xmin>666</xmin>
			<ymin>458</ymin>
			<xmax>855</xmax>
			<ymax>633</ymax>
		</bndbox>
	</object>
</annotation>
