<annotation><folder>frames</folder><filename>frame105</filename><path>/frames/frame105</path><source><database>Unknown</database></source><size><width>1920</width><height>1080</height><depth>3</depth></size><segmented>0</segmented><object><name>bee</name><pose>Unspecified</pose><truncated>0</truncated><difficult>0</difficult><bndbox><xmin>412</xmin><ymin>330</ymin><xmax>502</xmax><ymax>420</ymax></bndbox></object><object><name>bee</name><pose>Unspecified</pose><truncated>0</truncated><difficult>0</difficult><bndbox><xmin>1157</xmin><ymin>383</ymin><xmax>1241</xmax><ymax>467</ymax></bndbox></object><object><name>bee</name><pose>Unspecified</pose><truncated>0</truncated><difficult>0</difficult><bndbox><xmin>1189</xmin><ymin>443</ymin><xmax>1269</xmax><ymax>523</ymax></bndbox></object><object><name>bee</name><pose>Unspecified</pose><truncated>0</truncated><difficult>0</difficult><bndbox><xmin>1231</xmin><ymin>378</ymin><xmax>1311</xmax><ymax>458</ymax></bndbox></object><object><name>bee</name><pose>Unspecified</pose><truncated>0</truncated><difficult>0</difficult><bndbox><xmin>1173</xmin><ymin>162</ymin><xmax>1253</xmax><ymax>242</ymax></bndbox></object><object><name>bee</name><pose>Unspecified</pose><truncated>0</truncated><difficult>0</difficult><bndbox><xmin>990</xmin><ymin>402</ymin><xmax>1078</xmax><ymax>490</ymax></bndbox></object><object><name>bee</name><pose>Unspecified</pose><truncated>0</truncated><difficult>0</difficult><bndbox><xmin>436</xmin><ymin>-48</ymin><xmax>574</xmax><ymax>90</ymax></bndbox></object><object><name>bee</name><pose>Unspecified</pose><truncated>0</truncated><difficult>0</difficult><bndbox><xmin>1143</xmin><ymin>80</ymin><xmax>1225</xmax><ymax>162</ymax></bndbox></object></annotation>