<annotation><folder>frames</folder><filename>DSCN9960_frame209</filename><path>/frames/DSCN9960_frame209</path><source><database>Unknown</database></source><size><width>1920</width><height>1080</height><depth>3</depth></size><segmented>0</segmented><object><name>bee</name><pose>Unspecified</pose><truncated>0</truncated><difficult>0</difficult><bndbox><xmin>1188</xmin><ymin>192</ymin><xmax>1272</xmax><ymax>276</ymax></bndbox></object><object><name>bee</name><pose>Unspecified</pose><truncated>0</truncated><difficult>0</difficult><bndbox><xmin>77</xmin><ymin>512</ymin><xmax>159</xmax><ymax>594</ymax></bndbox></object><object><name>bee</name><pose>Unspecified</pose><truncated>0</truncated><difficult>0</difficult><bndbox><xmin>749</xmin><ymin>23</ymin><xmax>837</xmax><ymax>111</ymax></bndbox></object></annotation>