<annotation><folder>frames</folder><filename>DSCN9960_frame5</filename><path>/frames/DSCN9960_frame5</path><source><database>Unknown</database></source><size><width>1920</width><height>1080</height><depth>3</depth></size><segmented>0</segmented><object><name>bee</name><pose>Unspecified</pose><truncated>0</truncated><difficult>0</difficult><bndbox><xmin>444</xmin><ymin>195</ymin><xmax>546</xmax><ymax>297</ymax></bndbox></object><object><name>bee</name><pose>Unspecified</pose><truncated>0</truncated><difficult>0</difficult><bndbox><xmin>537</xmin><ymin>212</ymin><xmax>641</xmax><ymax>316</ymax></bndbox></object><object><name>bee</name><pose>Unspecified</pose><truncated>0</truncated><difficult>0</difficult><bndbox><xmin>451</xmin><ymin>457</ymin><xmax>541</xmax><ymax>547</ymax></bndbox></object><object><name>bee</name><pose>Unspecified</pose><truncated>0</truncated><difficult>0</difficult><bndbox><xmin>620</xmin><ymin>571</ymin><xmax>710</xmax><ymax>661</ymax></bndbox></object><object><name>bee</name><pose>Unspecified</pose><truncated>0</truncated><difficult>0</difficult><bndbox><xmin>447</xmin><ymin>675</ymin><xmax>531</xmax><ymax>759</ymax></bndbox></object><object><name>bee</name><pose>Unspecified</pose><truncated>0</truncated><difficult>0</difficult><bndbox><xmin>701</xmin><ymin>639</ymin><xmax>785</xmax><ymax>723</ymax></bndbox></object><object><name>bee</name><pose>Unspecified</pose><truncated>0</truncated><difficult>0</difficult><bndbox><xmin>543</xmin><ymin>810</ymin><xmax>627</xmax><ymax>894</ymax></bndbox></object><object><name>bee</name><pose>Unspecified</pose><truncated>0</truncated><difficult>0</difficult><bndbox><xmin>733</xmin><ymin>912</ymin><xmax>819</xmax><ymax>998</ymax></bndbox></object><object><name>bee</name><pose>Unspecified</pose><truncated>0</truncated><difficult>0</difficult><bndbox><xmin>813</xmin><ymin>950</ymin><xmax>905</xmax><ymax>1042</ymax></bndbox></object><object><name>bee</name><pose>Unspecified</pose><truncated>0</truncated><difficult>0</difficult><bndbox><xmin>286</xmin><ymin>728</ymin><xmax>390</xmax><ymax>832</ymax></bndbox></object><object><name>bee</name><pose>Unspecified</pose><truncated>0</truncated><difficult>0</difficult><bndbox><xmin>74</xmin><ymin>683</ymin><xmax>156</xmax><ymax>765</ymax></bndbox></object><object><name>bee</name><pose>Unspecified</pose><truncated>0</truncated><difficult>0</difficult><bndbox><xmin>661</xmin><ymin>431</ymin><xmax>739</xmax><ymax>509</ymax></bndbox></object><object><name>bee</name><pose>Unspecified</pose><truncated>0</truncated><difficult>0</difficult><bndbox><xmin>859</xmin><ymin>701</ymin><xmax>937</xmax><ymax>779</ymax></bndbox></object><object><name>bee</name><pose>Unspecified</pose><truncated>0</truncated><difficult>0</difficult><bndbox><xmin>1052</xmin><ymin>816</ymin><xmax>1130</xmax><ymax>894</ymax></bndbox></object><object><name>bee</name><pose>Unspecified</pose><truncated>0</truncated><difficult>0</difficult><bndbox><xmin>942</xmin><ymin>682</ymin><xmax>1020</xmax><ymax>760</ymax></bndbox></object><object><name>bee</name><pose>Unspecified</pose><truncated>0</truncated><difficult>0</difficult><bndbox><xmin>952</xmin><ymin>604</ymin><xmax>1030</xmax><ymax>682</ymax></bndbox></object><object><name>bee</name><pose>Unspecified</pose><truncated>0</truncated><difficult>0</difficult><bndbox><xmin>1177</xmin><ymin>966</ymin><xmax>1255</xmax><ymax>1044</ymax></bndbox></object><object><name>bee</name><pose>Unspecified</pose><truncated>0</truncated><difficult>0</difficult><bndbox><xmin>497</xmin><ymin>392</ymin><xmax>569</xmax><ymax>464</ymax></bndbox></object></annotation>